{
  "project_info": {
    "project_number": "221673003242",
    "firebase_url": "https://test-ae7be.firebaseio.com",
    "project_id": "test-ae7be",
    "storage_bucket": "test-ae7be.appspot.com"
  },
  "client": [
    {
      "client_info": {
        "mobilesdk_app_id": "1:221673003242:android:2241b06b39d72583fb1f93",
        "android_client_info": {
          "package_name": "com.example.myapplication"
        }
      },
      "oauth_client": [
        {
          "client_id": "221673003242-0f5o9avfe9jasjokujubppibmggghjhq.apps.googleusercontent.com",
          "client_type": 3
        }
      ],
      "api_key": [
        {
          "current_key": "AIzaSyCJnv4iBYqGW1Ogbihvq_ckDj1kOqK41io"
        }
      ],
      "services": {
        "appinvite_service": {
          "other_platform_oauth_client": [
            {
              "client_id": "221673003242-0f5o9avfe9jasjokujubppibmggghjhq.apps.googleusercontent.com",
              "client_type": 3
            }
          ]
        }
      }
    }
  ],
  "configuration_version": "1"
}